Metadata-Version: 2.1
Name: SomeToolspbc
Version: 3.3
Summary: some tools
Author: pbcat2022
Author-email: yuyao_100804@outlook.com
